odoo/addons/gamification_badge_report/README.rst
odoo/addons/gamification_badge_report/__init__.py
odoo/addons/gamification_badge_report/__manifest__.py
odoo/addons/gamification_badge_report/i18n/es.po
odoo/addons/gamification_badge_report/i18n/gamification_badge_report.pot
odoo/addons/gamification_badge_report/i18n/it.po
odoo/addons/gamification_badge_report/i18n/it_IT.po
odoo/addons/gamification_badge_report/readme/CONTRIBUTORS.rst
odoo/addons/gamification_badge_report/readme/CREDITS.rst
odoo/addons/gamification_badge_report/readme/DESCRIPTION.rst
odoo/addons/gamification_badge_report/report/__init__.py
odoo/addons/gamification_badge_report/report/gamification_badge_report.py
odoo/addons/gamification_badge_report/report/gamification_badge_report_view.xml
odoo/addons/gamification_badge_report/security/ir.model.access.csv
odoo/addons/gamification_badge_report/static/description/icon.png
odoo/addons/gamification_badge_report/static/description/index.html
odoo/addons/gamification_badge_report/tests/__init__.py
odoo/addons/gamification_badge_report/tests/test_gamification_badge_report.py
odoo14_addon_gamification_badge_report-14.0.1.0.1.dev8.dist-info/METADATA
odoo14_addon_gamification_badge_report-14.0.1.0.1.dev8.dist-info/WHEEL
odoo14_addon_gamification_badge_report-14.0.1.0.1.dev8.dist-info/top_level.txt
odoo14_addon_gamification_badge_report-14.0.1.0.1.dev8.dist-info/RECORD
