Metadata-Version: 2.1
Name: odoo14-addon-gamification_badge_report
Version: 14.0.1.0.1.dev8
Summary: Send Email to all the Employees with all the award given in the last week.
Home-page: https://github.com/OCA/hr
Author: Open Source Integrators, Serpent Consulting Services, Odoo Community Association (OCA)
Author-email: support@odoo-community.org
License: AGPL-3
Classifier: Programming Language :: Python
Classifier: Framework :: Odoo
Classifier: Framework :: Odoo :: 14.0
Classifier: License :: OSI Approved :: GNU Affero General Public License v3
Requires-Python: >=3.6
Requires-Dist: odoo<14.1dev,>=14.0a
